MANIFEST.in
README.rst
setup.cfg
setup.py
onyxjokes/__init__.py
onyxjokes/jokes_de.py
onyxjokes/jokes_en.py
onyxjokes/jokes_es.py
onyxjokes/jokes_fr.py
onyxjokes/onyxjokes.py
onyxjokes.egg-info/PKG-INFO
onyxjokes.egg-info/SOURCES.txt
onyxjokes.egg-info/dependency_links.txt
onyxjokes.egg-info/top_level.txt
scripts/onyxjoke
scripts/onyxjokes