Metadata-Version: 1.1
Name: onyxjokes
Version: 0.0.6
Summary: Add more language to Pyjokes by Pyjokes Society
Home-page: https://github.com/pyjokes/pyjokes
Author: Pyjokes Society
Author-email: UNKNOWN
License: BSD
Keywords: pyjokes,jokes,onyxjokes,onyx
Platform: UNKNOWN
Classifier: Development Status :: 4 - Beta
Classifier: Topic :: Utilities
Classifier: License :: OSI Approved :: BSD License
Classifier: Programming Language :: Python :: 2
